{
  "id": "e3798f81-d5b3-4fb8-b572-6039d383d4c2",
  "prevId": "43011a53-b029-412d-9bb9-be43249dc803",
  "version": "7",
  "dialect": "postgresql",
  "tables": {
    "public.categories": {
      "name": "categories",
      "schema": "",
      "columns": {
        "id": {
          "name": "id",
          "type": "serial",
          "primaryKey": true,
          "notNull": true
        },
        "name": {
          "name": "name",
          "type": "varchar(120)",
          "primaryKey": false,
          "notNull": true
        },
        "slug": {
          "name": "slug",
          "type": "varchar(140)",
          "primaryKey": false,
          "notNull": true
        },
        "created_at": {
          "name": "created_at",
          "type": "timestamp with time zone",
          "primaryKey": false,
          "notNull": true,
          "default": "now()"
        }
      },
      "indexes": {
        "categories_name_u": {
          "name": "categories_name_u",
          "columns": [
            {
              "expression": "name",
              "isExpression": false,
              "asc": true,
              "nulls": "last"
            }
          ],
          "isUnique": true,
          "concurrently": false,
          "method": "btree",
          "with": {}
        },
        "categories_slug_u": {
          "name": "categories_slug_u",
          "columns": [
            {
              "expression": "slug",
              "isExpression": false,
              "asc": true,
              "nulls": "last"
            }
          ],
          "isUnique": true,
          "concurrently": false,
          "method": "btree",
          "with": {}
        }
      },
      "foreignKeys": {},
      "compositePrimaryKeys": {},
      "uniqueConstraints": {},
      "policies": {},
      "checkConstraints": {},
      "isRLSEnabled": false
    },
    "public.choices": {
      "name": "choices",
      "schema": "",
      "columns": {
        "id": {
          "name": "id",
          "type": "serial",
          "primaryKey": true,
          "notNull": true
        },
        "question_id": {
          "name": "question_id",
          "type": "integer",
          "primaryKey": false,
          "notNull": true
        },
        "text": {
          "name": "text",
          "type": "text",
          "primaryKey": false,
          "notNull": true
        },
        "is_correct": {
          "name": "is_correct",
          "type": "boolean",
          "primaryKey": false,
          "notNull": true,
          "default": false
        }
      },
      "indexes": {},
      "foreignKeys": {
        "choices_question_id_questions_id_fk": {
          "name": "choices_question_id_questions_id_fk",
          "tableFrom": "choices",
          "tableTo": "questions",
          "columnsFrom": [
            "question_id"
          ],
          "columnsTo": [
            "id"
          ],
          "onDelete": "cascade",
          "onUpdate": "no action"
        }
      },
      "compositePrimaryKeys": {},
      "uniqueConstraints": {},
      "policies": {},
      "checkConstraints": {},
      "isRLSEnabled": false
    },
    "public.materials": {
      "name": "materials",
      "schema": "",
      "columns": {
        "id": {
          "name": "id",
          "type": "serial",
          "primaryKey": true,
          "notNull": true
        },
        "title": {
          "name": "title",
          "type": "varchar(180)",
          "primaryKey": false,
          "notNull": true
        },
        "slug": {
          "name": "slug",
          "type": "varchar(180)",
          "primaryKey": false,
          "notNull": true
        },
        "content_md": {
          "name": "content_md",
          "type": "text",
          "primaryKey": false,
          "notNull": true
        },
        "published": {
          "name": "published",
          "type": "boolean",
          "primaryKey": false,
          "notNull": true,
          "default": true
        },
        "category_id": {
          "name": "category_id",
          "type": "integer",
          "primaryKey": false,
          "notNull": true
        },
        "author_id": {
          "name": "author_id",
          "type": "integer",
          "primaryKey": false,
          "notNull": true
        },
        "created_at": {
          "name": "created_at",
          "type": "timestamp with time zone",
          "primaryKey": false,
          "notNull": true,
          "default": "now()"
        }
      },
      "indexes": {},
      "foreignKeys": {
        "materials_category_id_categories_id_fk": {
          "name": "materials_category_id_categories_id_fk",
          "tableFrom": "materials",
          "tableTo": "categories",
          "columnsFrom": [
            "category_id"
          ],
          "columnsTo": [
            "id"
          ],
          "onDelete": "set null",
          "onUpdate": "no action"
        },
        "materials_author_id_users_id_fk": {
          "name": "materials_author_id_users_id_fk",
          "tableFrom": "materials",
          "tableTo": "users",
          "columnsFrom": [
            "author_id"
          ],
          "columnsTo": [
            "id"
          ],
          "onDelete": "cascade",
          "onUpdate": "no action"
        }
      },
      "compositePrimaryKeys": {},
      "uniqueConstraints": {
        "materials_slug_unique": {
          "name": "materials_slug_unique",
          "nullsNotDistinct": false,
          "columns": [
            "slug"
          ]
        }
      },
      "policies": {},
      "checkConstraints": {},
      "isRLSEnabled": false
    },
    "public.questions": {
      "name": "questions",
      "schema": "",
      "columns": {
        "id": {
          "name": "id",
          "type": "serial",
          "primaryKey": true,
          "notNull": true
        },
        "quiz_id": {
          "name": "quiz_id",
          "type": "integer",
          "primaryKey": false,
          "notNull": true
        },
        "prompt": {
          "name": "prompt",
          "type": "text",
          "primaryKey": false,
          "notNull": true
        },
        "explain": {
          "name": "explain",
          "type": "text",
          "primaryKey": false,
          "notNull": false
        },
        "order_idx": {
          "name": "order_idx",
          "type": "integer",
          "primaryKey": false,
          "notNull": true
        }
      },
      "indexes": {},
      "foreignKeys": {
        "questions_quiz_id_quizzes_id_fk": {
          "name": "questions_quiz_id_quizzes_id_fk",
          "tableFrom": "questions",
          "tableTo": "quizzes",
          "columnsFrom": [
            "quiz_id"
          ],
          "columnsTo": [
            "id"
          ],
          "onDelete": "cascade",
          "onUpdate": "no action"
        }
      },
      "compositePrimaryKeys": {},
      "uniqueConstraints": {},
      "policies": {},
      "checkConstraints": {},
      "isRLSEnabled": false
    },
    "public.quiz_answers": {
      "name": "quiz_answers",
      "schema": "",
      "columns": {
        "id": {
          "name": "id",
          "type": "serial",
          "primaryKey": true,
          "notNull": true
        },
        "attempt_id": {
          "name": "attempt_id",
          "type": "integer",
          "primaryKey": false,
          "notNull": true
        },
        "question_id": {
          "name": "question_id",
          "type": "integer",
          "primaryKey": false,
          "notNull": true
        },
        "choice_id": {
          "name": "choice_id",
          "type": "integer",
          "primaryKey": false,
          "notNull": true
        },
        "is_correct": {
          "name": "is_correct",
          "type": "boolean",
          "primaryKey": false,
          "notNull": true,
          "default": false
        }
      },
      "indexes": {},
      "foreignKeys": {
        "quiz_answers_attempt_id_quiz_attempts_id_fk": {
          "name": "quiz_answers_attempt_id_quiz_attempts_id_fk",
          "tableFrom": "quiz_answers",
          "tableTo": "quiz_attempts",
          "columnsFrom": [
            "attempt_id"
          ],
          "columnsTo": [
            "id"
          ],
          "onDelete": "cascade",
          "onUpdate": "no action"
        },
        "quiz_answers_question_id_questions_id_fk": {
          "name": "quiz_answers_question_id_questions_id_fk",
          "tableFrom": "quiz_answers",
          "tableTo": "questions",
          "columnsFrom": [
            "question_id"
          ],
          "columnsTo": [
            "id"
          ],
          "onDelete": "cascade",
          "onUpdate": "no action"
        },
        "quiz_answers_choice_id_choices_id_fk": {
          "name": "quiz_answers_choice_id_choices_id_fk",
          "tableFrom": "quiz_answers",
          "tableTo": "choices",
          "columnsFrom": [
            "choice_id"
          ],
          "columnsTo": [
            "id"
          ],
          "onDelete": "cascade",
          "onUpdate": "no action"
        }
      },
      "compositePrimaryKeys": {},
      "uniqueConstraints": {},
      "policies": {},
      "checkConstraints": {},
      "isRLSEnabled": false
    },
    "public.quiz_attempts": {
      "name": "quiz_attempts",
      "schema": "",
      "columns": {
        "id": {
          "name": "id",
          "type": "serial",
          "primaryKey": true,
          "notNull": true
        },
        "user_id": {
          "name": "user_id",
          "type": "integer",
          "primaryKey": false,
          "notNull": true
        },
        "quiz_id": {
          "name": "quiz_id",
          "type": "integer",
          "primaryKey": false,
          "notNull": true
        },
        "score": {
          "name": "score",
          "type": "integer",
          "primaryKey": false,
          "notNull": true
        },
        "total": {
          "name": "total",
          "type": "integer",
          "primaryKey": false,
          "notNull": true
        },
        "duration_s": {
          "name": "duration_s",
          "type": "integer",
          "primaryKey": false,
          "notNull": true,
          "default": 0
        },
        "created_at": {
          "name": "created_at",
          "type": "timestamp with time zone",
          "primaryKey": false,
          "notNull": true,
          "default": "now()"
        }
      },
      "indexes": {},
      "foreignKeys": {
        "quiz_attempts_user_id_users_id_fk": {
          "name": "quiz_attempts_user_id_users_id_fk",
          "tableFrom": "quiz_attempts",
          "tableTo": "users",
          "columnsFrom": [
            "user_id"
          ],
          "columnsTo": [
            "id"
          ],
          "onDelete": "cascade",
          "onUpdate": "no action"
        },
        "quiz_attempts_quiz_id_quizzes_id_fk": {
          "name": "quiz_attempts_quiz_id_quizzes_id_fk",
          "tableFrom": "quiz_attempts",
          "tableTo": "quizzes",
          "columnsFrom": [
            "quiz_id"
          ],
          "columnsTo": [
            "id"
          ],
          "onDelete": "cascade",
          "onUpdate": "no action"
        }
      },
      "compositePrimaryKeys": {},
      "uniqueConstraints": {},
      "policies": {},
      "checkConstraints": {},
      "isRLSEnabled": false
    },
    "public.quizzes": {
      "name": "quizzes",
      "schema": "",
      "columns": {
        "id": {
          "name": "id",
          "type": "serial",
          "primaryKey": true,
          "notNull": true
        },
        "title": {
          "name": "title",
          "type": "varchar(180)",
          "primaryKey": false,
          "notNull": true
        },
        "description": {
          "name": "description",
          "type": "text",
          "primaryKey": false,
          "notNull": false
        },
        "published": {
          "name": "published",
          "type": "boolean",
          "primaryKey": false,
          "notNull": true,
          "default": true
        },
        "category_id": {
          "name": "category_id",
          "type": "integer",
          "primaryKey": false,
          "notNull": true
        },
        "author_id": {
          "name": "author_id",
          "type": "integer",
          "primaryKey": false,
          "notNull": true
        },
        "created_at": {
          "name": "created_at",
          "type": "timestamp with time zone",
          "primaryKey": false,
          "notNull": true,
          "default": "now()"
        }
      },
      "indexes": {},
      "foreignKeys": {
        "quizzes_category_id_categories_id_fk": {
          "name": "quizzes_category_id_categories_id_fk",
          "tableFrom": "quizzes",
          "tableTo": "categories",
          "columnsFrom": [
            "category_id"
          ],
          "columnsTo": [
            "id"
          ],
          "onDelete": "set null",
          "onUpdate": "no action"
        },
        "quizzes_author_id_users_id_fk": {
          "name": "quizzes_author_id_users_id_fk",
          "tableFrom": "quizzes",
          "tableTo": "users",
          "columnsFrom": [
            "author_id"
          ],
          "columnsTo": [
            "id"
          ],
          "onDelete": "cascade",
          "onUpdate": "no action"
        }
      },
      "compositePrimaryKeys": {},
      "uniqueConstraints": {},
      "policies": {},
      "checkConstraints": {},
      "isRLSEnabled": false
    },
    "public.users": {
      "name": "users",
      "schema": "",
      "columns": {
        "id": {
          "name": "id",
          "type": "serial",
          "primaryKey": true,
          "notNull": true
        },
        "name": {
          "name": "name",
          "type": "varchar(120)",
          "primaryKey": false,
          "notNull": false
        },
        "email": {
          "name": "email",
          "type": "varchar(190)",
          "primaryKey": false,
          "notNull": true
        },
        "password_hash": {
          "name": "password_hash",
          "type": "text",
          "primaryKey": false,
          "notNull": true
        },
        "role": {
          "name": "role",
          "type": "role",
          "typeSchema": "public",
          "primaryKey": false,
          "notNull": true,
          "default": "'USER'"
        },
        "created_at": {
          "name": "created_at",
          "type": "timestamp with time zone",
          "primaryKey": false,
          "notNull": true,
          "default": "now()"
        }
      },
      "indexes": {},
      "foreignKeys": {},
      "compositePrimaryKeys": {},
      "uniqueConstraints": {
        "users_email_unique": {
          "name": "users_email_unique",
          "nullsNotDistinct": false,
          "columns": [
            "email"
          ]
        }
      },
      "policies": {},
      "checkConstraints": {},
      "isRLSEnabled": false
    },
    "public.words": {
      "name": "words",
      "schema": "",
      "columns": {
        "id": {
          "name": "id",
          "type": "serial",
          "primaryKey": true,
          "notNull": true
        },
        "term": {
          "name": "term",
          "type": "varchar(160)",
          "primaryKey": false,
          "notNull": true
        },
        "meaning": {
          "name": "meaning",
          "type": "text",
          "primaryKey": false,
          "notNull": true
        },
        "example": {
          "name": "example",
          "type": "text",
          "primaryKey": false,
          "notNull": false
        },
        "category_id": {
          "name": "category_id",
          "type": "integer",
          "primaryKey": false,
          "notNull": true
        },
        "created_at": {
          "name": "created_at",
          "type": "timestamp with time zone",
          "primaryKey": false,
          "notNull": true,
          "default": "now()"
        }
      },
      "indexes": {},
      "foreignKeys": {
        "words_category_id_categories_id_fk": {
          "name": "words_category_id_categories_id_fk",
          "tableFrom": "words",
          "tableTo": "categories",
          "columnsFrom": [
            "category_id"
          ],
          "columnsTo": [
            "id"
          ],
          "onDelete": "cascade",
          "onUpdate": "no action"
        }
      },
      "compositePrimaryKeys": {},
      "uniqueConstraints": {},
      "policies": {},
      "checkConstraints": {},
      "isRLSEnabled": false
    }
  },
  "enums": {
    "public.role": {
      "name": "role",
      "schema": "public",
      "values": [
        "USER",
        "ADMIN"
      ]
    }
  },
  "schemas": {},
  "sequences": {},
  "roles": {},
  "policies": {},
  "views": {},
  "_meta": {
    "columns": {},
    "schemas": {},
    "tables": {}
  }
}